docblock/__init__.py
docblock/grammar.py
docblock/parse.py
docblock/show_versions.py
docblock/utils.py
docblock-0.1.6.dist-info/LICENSE.md
docblock-0.1.6.dist-info/METADATA
docblock-0.1.6.dist-info/WHEEL
docblock-0.1.6.dist-info/RECORD
