Metadata-Version: 2.3
Name: docblock
Version: 0.1.6
Summary: Reads and parses documentation from header files in pure Python.
License: MIT
Author: Niels Wouda
Author-email: nielswouda@gmail.com
Requires-Python: >=3.8,<4.0
Classifier: Development Status :: 5 - Production/Stable
Classifier: Intended Audience :: Developers
Classifier: License :: OSI Approved :: MIT License
Classifier: Programming Language :: Python :: 3
Classifier: Programming Language :: Python :: 3.8
Classifier: Programming Language :: Python :: 3.9
Classifier: Programming Language :: Python :: 3.10
Classifier: Programming Language :: Python :: 3.11
Classifier: Programming Language :: Python :: 3.12
Classifier: Programming Language :: Python :: 3.13
Classifier: Topic :: Software Development
Requires-Dist: pyparsing (>=3.0.6,<4.0.0)
Project-URL: Repository, https://github.com/N-Wouda/docblock
Project-URL: Tracker, https://github.com/N-Wouda/docblock/issues
